datamop/__init__.py
datamop/column_encoder.py
datamop/column_scaler.py
datamop/sweep_nulls.py
datamop-1.1.2.dist-info/LICENSE
datamop-1.1.2.dist-info/METADATA
datamop-1.1.2.dist-info/WHEEL
datamop-1.1.2.dist-info/RECORD
