Metadata-Version: 2.3
Name: datamop
Version: 1.1.2
Summary: A package containing tools for robust data cleaning.
License: MIT
Author: Sepehr Heydarian, Ximin Xu, Essie Zhang
Requires-Python: >=3.11,<4.0
Classifier: License :: OSI Approved :: MIT License
Classifier: Programming Language :: Python :: 3
Classifier: Programming Language :: Python :: 3.11
Classifier: Programming Language :: Python :: 3.12
Classifier: Programming Language :: Python :: 3.13
Requires-Dist: pandas (>=2.2.3,<3.0.0)
